README.md
setup.cfg
setup.py
taobaopy/__init__.py
taobaopy/taobao.py
taobaopy/version.py
taobaopy.egg-info/PKG-INFO
taobaopy.egg-info/SOURCES.txt
taobaopy.egg-info/dependency_links.txt
taobaopy.egg-info/not-zip-safe
taobaopy.egg-info/requires.txt
taobaopy.egg-info/top_level.txt