Metadata-Version: 1.1
Name: taobaopy
Version: 6.0.1
Summary: A Very Easy Learned Python SDK For TaoBao.com API
Home-page: https://github.com/sempr/taobaopy
Author: Sempr Wang
Author-email: taobao-pysdk@1e20.com
License: BSD
Platform: any
Classifier: Development Status :: 5 - Production/Stable
Classifier: Intended Audience :: Developers
Classifier: Natural Language :: English
Classifier: Programming Language :: Python
Classifier: Programming Language :: Python :: 2
Classifier: Programming Language :: Python :: 2.7
Classifier: Programming Language :: Python :: 3
Classifier: Programming Language :: Python :: 3.6
